tidytxt/__init__.py
tidytxt/cli.py
tidytxt/tidytxt.py
tidytxt-0.1.1.dist-info/AUTHORS.rst
tidytxt-0.1.1.dist-info/LICENSE
tidytxt-0.1.1.dist-info/METADATA
tidytxt-0.1.1.dist-info/WHEEL
tidytxt-0.1.1.dist-info/entry_points.txt
tidytxt-0.1.1.dist-info/top_level.txt
tidytxt-0.1.1.dist-info/RECORD
