Metadata-Version: 2.1
Name: tidytxt
Version: 0.1.1
Summary: A python package for tidytext analysis.
Home-page: https://github.com/jstonge/tidytxt
Author: Jonathan St-Onge
Author-email: jonathanstonge7@gmail.com
License: MIT license
Keywords: tidytxt
Platform: UNKNOWN
Classifier: Development Status :: 2 - Pre-Alpha
Classifier: Intended Audience :: Developers
Classifier: License :: OSI Approved :: MIT License
Classifier: Natural Language :: English
Classifier: Programming Language :: Python :: 3
Classifier: Programming Language :: Python :: 3.6
Classifier: Programming Language :: Python :: 3.7
Classifier: Programming Language :: Python :: 3.8
Requires-Python: >=3.6
License-File: LICENSE
License-File: AUTHORS.rst
Requires-Dist: Click (>=7.0)
Requires-Dist: spacy (>=3.0)
Requires-Dist: numpy (>1.0)
Requires-Dist: matplotlib (>3.0)
Requires-Dist: pandas (>1.0)
Requires-Dist: seaborn (>0.11)
